constellix/__init__.py
constellix/exceptions.py
constellix/skeleton.py
constellix/API/__init__.py
constellix/API/main.py
constellix/domains/__init__.py
constellix/domains/domain.py
constellix/domains/domains.py
constellix/domains/record/__init__.py
constellix/domains/record/const.py
constellix/domains/record/record.py
constellix/domains/record/type/__init__.py
constellix/domains/record/type/a.py
constellix/domains/record/type/aaaa.py
constellix/domains/record/type/main.py
constellix/protocol/__init__.py
constellix/protocol/protocol.py
constellix-0.0.4.dist-info/AUTHORS.rst
constellix-0.0.4.dist-info/LICENSE.txt
constellix-0.0.4.dist-info/METADATA
constellix-0.0.4.dist-info/WHEEL
constellix-0.0.4.dist-info/top_level.txt
constellix-0.0.4.dist-info/RECORD
