Metadata-Version: 2.1
Name: constellix
Version: 0.0.4
Summary: Unofficial library to interface with the Constellix API
Home-page: https://github.com/aperim/python-constellix
Author: Troy Kelly
Author-email: troy@aperim.com
License: cc0
Project-URL: Documentation, https://github.com/aperim/python-constellix/wiki
Project-URL: Issues, https://github.com/aperim/python-constellix/issues
Platform: any
Classifier: Development Status :: 4 - Beta
Classifier: Programming Language :: Python
Requires-Dist: requests
Requires-Dist: backoff
Provides-Extra: testing
Requires-Dist: pytest ; extra == 'testing'
Requires-Dist: pytest-cov ; extra == 'testing'
